local_reassembly/__init__.py
local_reassembly/cli.py
local_reassembly/src.py
local_reassembly/versions.py
local_reassembly-0.0.7.dist-info/LICENSE
local_reassembly-0.0.7.dist-info/METADATA
local_reassembly-0.0.7.dist-info/WHEEL
local_reassembly-0.0.7.dist-info/entry_points.txt
local_reassembly-0.0.7.dist-info/top_level.txt
local_reassembly-0.0.7.dist-info/RECORD
