Metadata-Version: 2.1
Name: local_reassembly
Version: 0.0.7
Summary: Locally reassembling haplotypes from BAM files generated by WGS data.
Home-page: https://github.com/SouthernCD/local_reassembly
Author: Yuxing Xu
Author-email: xuyuxing@mail.kib.ac.cn
Requires-Python: >=3.5
License-File: LICENSE
Requires-Dist: biopython ==1.80
Requires-Dist: bcbio-gff ==0.7.1
